mkdocs_drawio_exporter/__init__.py
mkdocs_drawio_exporter/exporter.py
mkdocs_drawio_exporter/plugin.py
mkdocs_drawio_exporter/tests/__init__.py
mkdocs_drawio_exporter/tests/exporter.py
mkdocs_drawio_exporter-0.10.1.dist-info/LICENSE.md
mkdocs_drawio_exporter-0.10.1.dist-info/METADATA
mkdocs_drawio_exporter-0.10.1.dist-info/WHEEL
mkdocs_drawio_exporter-0.10.1.dist-info/entry_points.txt
mkdocs_drawio_exporter-0.10.1.dist-info/RECORD
