Metadata-Version: 2.1
Name: mkdocs-drawio-exporter
Version: 0.10.1
Summary: Exports your Draw.io diagrams at build time for easier embedding into your documentation
License: MIT
Author: Luke Carrier
Author-email: luke@carrier.family
Requires-Python: >=3.8
Classifier: Development Status :: 5 - Production/Stable
Classifier: Environment :: Console
Classifier: Environment :: Web Environment
Classifier: Intended Audience :: Developers
Classifier: License :: OSI Approved :: MIT License
Classifier: Operating System :: OS Independent
Classifier: Programming Language :: Python
Classifier: Programming Language :: Python :: 3
Classifier: Programming Language :: Python :: 3.8
Classifier: Programming Language :: Python :: 3.9
Classifier: Programming Language :: Python :: 3.10
Classifier: Programming Language :: Python :: 3.11
Classifier: Programming Language :: Python :: 3.12
Classifier: Programming Language :: Python :: 3.13
Classifier: Programming Language :: Python :: 3 :: Only
Classifier: Topic :: Documentation
Classifier: Topic :: Text Processing
Requires-Dist: click (>=7.1.2)
Requires-Dist: jinja2 (>=3.1.3)
Requires-Dist: livereload (>=2.6.3)
Requires-Dist: markdown (>=3.3.4)
Requires-Dist: markupsafe (>=2.1.5)
Requires-Dist: mkdocs (>=1.3.0)
Requires-Dist: pyyaml (>=6.0.1)
Requires-Dist: six (>=1.16.0)
Requires-Dist: tornado (>=6.3.3)
Project-URL: History, https://github.com/LukeCarrier/mkdocs-drawio-exporter/blob/master/CHANGELOG.md
Project-URL: Issues, https://github.com/LukeCarrier/mkdocs-drawio-exporter/issues
Project-URL: documentation, https://github.com/LukeCarrier/mkdocs-drawio-exporter
Project-URL: homepage, https://github.com/LukeCarrier/mkdocs-drawio-exporter
Project-URL: repository, https://github.com/LukeCarrier/mkdocs-drawio-exporter
